{
    "variants": 
    {
        "burning=false,facing=north": { "model": "azr:sintering_furnace" },
        "burning=false,facing=east": { "model": "azr:sintering_furnace", "y": 90 },
        "burning=false,facing=south": { "model": "azr:sintering_furnace", "y": 180 },
        "burning=false,facing=west": { "model": "azr:sintering_furnace", "y": 270 },
        "burning=true,facing=north": { "model": "azr:lit_sintering_furnace" },
        "burning=true,facing=east": { "model": "azr:lit_sintering_furnace", "y": 90 },
        "burning=true,facing=south": { "model": "azr:lit_sintering_furnace", "y": 180 },
        "burning=true,facing=west": { "model": "azr:lit_sintering_furnace", "y":270  }
    }
}